multivariate_cwru/__init__.py
multivariate_cwru/datafiles.txt
multivariate_cwru-1.4.dist-info/METADATA
multivariate_cwru-1.4.dist-info/WHEEL
multivariate_cwru-1.4.dist-info/top_level.txt
multivariate_cwru-1.4.dist-info/RECORD
