Metadata-Version: 2.1
Name: multivariate_cwru
Version: 1.4
Summary: Preprocessed CWRU Bearing Dataset for multivariate signals
Home-page: https://github.com/JvdHoogen/multivariate_cwru
Author: Jurgen van den Hoogen
Author-email: jurgenvandenhoogen@hotmail.com
Classifier: Programming Language :: Python :: 3
Classifier: License :: OSI Approved :: MIT License
Classifier: Operating System :: OS Independent
Requires-Python: >=3.6
